{"Users":[{"User":"apprabbit","Email":"megamark16@gmail.com","TimeZone":"-6.00","Company":"AppRabbit","IsAccountOwner":1,"CreateForms":1,"CreateReports":1,"CreateThemes":1,"AdminAccess":"1","Image":"animal_10","ApiKey":"C0BN-5BYC-I30C-U95X","LinkForms":"https:\/\/apprabbit.wufoo.com\/api\/v3\/forms.json","LinkReports":"https:\/\/apprabbit.wufoo.com\/api\/v3\/reports.json","Hash":"p-b2q2793","ImageUrlBig":"https:\/\/wufoo.com\/images\/avatars\/big\/animal_10.png","ImageUrlSmall":"https:\/\/wufoo.com\/images\/avatars\/small\/animal_10.png","HttpsEnabled":0}]}